archaic/__init__.py
archaic/_info.py
archaic/_models.py
archaic/_predicate.py
archaic/feature_class.py
archaic-0.1.3.dist-info/METADATA
archaic-0.1.3.dist-info/WHEEL
archaic-0.1.3.dist-info/top_level.txt
archaic-0.1.3.dist-info/RECORD
